src/__init__.py
src/__version__.py
src/attribute_setter.py
src/indicator_healtharea_updater.py
src/program_orgunit_assigner.py
src/scan_event_mismatches.py
src/user_message.py
src/utils.py
hnqis_cli-0.2.1.dist-info/LICENCE.txt
hnqis_cli-0.2.1.dist-info/METADATA
hnqis_cli-0.2.1.dist-info/WHEEL
hnqis_cli-0.2.1.dist-info/entry_points.txt
hnqis_cli-0.2.1.dist-info/top_level.txt
hnqis_cli-0.2.1.dist-info/RECORD
